corderius_play-2.6.1.dist-info/licenses/LICENSE
play/__init__.py
play/blank_image.png
play/globals.py
play/loop.py
play/api/__init__.py
play/api/events.py
play/api/generators.py
play/api/random.py
play/api/utils.py
play/callback/__init__.py
play/callback/callback_helpers.py
play/callback/collision_callbacks.py
play/core/__init__.py
play/core/controller_loop.py
play/core/game_loop_wrapper.py
play/core/mouse_loop.py
play/core/physics_loop.py
play/core/sprites_loop.py
play/db/__init__.py
play/io/__init__.py
play/io/controllers.py
play/io/keypress.py
play/io/logging.py
play/io/mouse.py
play/io/screen.py
play/objects/__init__.py
play/objects/box.py
play/objects/circle.py
play/objects/image.py
play/objects/line.py
play/objects/sound.py
play/objects/sprite.py
play/objects/text.py
play/physics/__init__.py
play/utils/__init__.py
play/utils/async_helpers.py
corderius_play-2.6.1.dist-info/METADATA
corderius_play-2.6.1.dist-info/WHEEL
corderius_play-2.6.1.dist-info/top_level.txt
corderius_play-2.6.1.dist-info/RECORD
