Metadata-Version: 2.4
Name: corderius-play
Version: 2.6.1
Summary: The easiest way to make games and media projects in Python.
Home-page: https://github.com/Corderius-College-Amersfoort/play
Author: koen1711
Author-email: koenvurk1711@gmail.com
License: MIT
Classifier: License :: OSI Approved :: MIT License
Classifier: Programming Language :: Python :: 3
Classifier: Programming Language :: Python :: 3.7
Requires-Python: >=3.10
License-File: LICENSE
Requires-Dist: numpy==2.2.6
Requires-Dist: pygame-ce==2.5.3
Requires-Dist: pymunk==6.11.1
Requires-Dist: pytest==8.3.5
Requires-Dist: screeninfo==0.8.1
Dynamic: author
Dynamic: author-email
Dynamic: classifier
Dynamic: description
Dynamic: description-content-type
Dynamic: home-page
Dynamic: license
Dynamic: license-file
Dynamic: requires-dist
Dynamic: requires-python
Dynamic: summary
